cosmospectra/SIMunits.py
cosmospectra/__init__.py
cosmospectra/bispectrum.py
cosmospectra/bispectrum_direct.py
cosmospectra/power_spect_fast.py
cosmospectra/power_spect_response.py
cosmospectra/toymodel.py
cosmospectra/useful.py
cosmospectra/useful_speedup.py
cosmospectra-0.1.1.dist-info/METADATA
cosmospectra-0.1.1.dist-info/WHEEL
cosmospectra-0.1.1.dist-info/top_level.txt
cosmospectra-0.1.1.dist-info/RECORD
