Metadata-Version: 2.1
Name: cosmospectra
Version: 0.1.1
Home-page: https://github.com/sambit-giri/cosmospectra.git
Author: Sambit Giri
Author-email: sambit.giri@astro.su.se
Requires-Dist: numpy
Requires-Dist: scipy
Requires-Dist: astropy
Requires-Dist: numba
